work_weixin/__init__.py
work_weixin/client.py
work_weixin/consts.py
work_weixin/exceptions.py
work_weixin/utils.py
work_weixin-0.0.2.3.dist-info/METADATA
work_weixin-0.0.2.3.dist-info/WHEEL
work_weixin-0.0.2.3.dist-info/top_level.txt
work_weixin-0.0.2.3.dist-info/RECORD
