Metadata-Version: 2.1
Name: work-weixin
Version: 0.0.2.3
Summary: 企业微信开发接口
Home-page: https://github.com/haifengat/work_weixin
Author: HaiFeng
Author-email: haifengat@vip.qq.com
License: MIT License
Platform: any
Classifier: Programming Language :: Python :: 3
Classifier: Programming Language :: Python :: 3.4
Classifier: Programming Language :: Python :: 3.5
Classifier: Programming Language :: Python :: 3.6
Classifier: Programming Language :: Python :: 3.7
Classifier: License :: OSI Approved :: MIT License
Classifier: Operating System :: OS Independent
Requires-Python: >=3.4.0
Requires-Dist: setuptools (==40.2.0)
Requires-Dist: requests-toolbelt (==0.8.0)
Requires-Dist: requests (==2.19.1)
Requires-Dist: PyYAML (==3.13)
